LICENSE
README.md
setup.py
eyeson/__init__.py
eyeson/eyeson.py
eyeson/test.py
eyeson.egg-info/PKG-INFO
eyeson.egg-info/SOURCES.txt
eyeson.egg-info/dependency_links.txt
eyeson.egg-info/top_level.txt