Metadata-Version: 2.1
Name: eyeson
Version: 0.0.5
Summary: Eyeson API Python SDK
Home-page: https://www.eyeson.com/
Author: Dinesh Shenoy
Author-email: dinesh.shenoy@eyeson.com
License: GNU v3
Platform: UNKNOWN
License-File: LICENSE
